setup.py
mindspeed/main.py
mindspeed.egg-info/PKG-INFO
mindspeed.egg-info/SOURCES.txt
mindspeed.egg-info/dependency_links.txt
mindspeed.egg-info/top_level.txt