Metadata-Version: 2.4
Name: mindspeed
Version: 0.0.1.dev1
Summary: MindSpeed for LLMs of Ascend
Home-page: https://gitcode.com/Ascend/MindSpeed
License: Apache
Classifier: Intended Audience :: Developers
Classifier: Intended Audience :: Science/Research
Classifier: Intended Audience :: Information Technology
Classifier: Programming Language :: Python :: 3
Classifier: License :: OSI Approved :: Apache Software License
Classifier: Operating System :: OS Independent
Requires-Python: >= 3.7
Dynamic: classifier
Dynamic: description
Dynamic: description-content-type
Dynamic: home-page
Dynamic: license
Dynamic: requires-python
Dynamic: summary
